Workbook

Sheet Dashboard
B1: SUMMIT RIDGE CONSTRUCTION LLC
B2: Monthly Financial Brief — Reporting Period: July 2026 — Prepared by Patino Davila Advisory
B4: REVENUE (JUL) | D4: GROSS MARGIN | F4: NET INCOME (JUL)
B5: ='Monthly P&L'!G5 | D5: ='Monthly P&L'!G12 | F5: ='Monthly P&L'!G21
B6: +9.7% vs Jun | D6: 6-mo avg 27.7% | F6: 11.7% net margin
B8: CASH ON HAND | D8: 13-WEEK LOW CASH | F8: SIGNED BACKLOG
B9: ='13-Week Cash Flow'!B5 | D9: =MIN('13-Week Cash Flow'!B19:N19) | F9: 1815000
B10: as of Jul 31 | D10: week of Oct 6 — action needed | F10: ~8.3 months coverage
B12: REVENUE — TRAILING 6 MONTHS | E12: WORKING CAPITAL SNAPSHOT
J13: Feb-26 | K13: Mar-26 | L13: Apr-26 | M13: May-26 | N13: Jun-26 | O13: Jul-26
E14: Accounts Receivable | G14: 312000 | J14: ='Monthly P&L'!B5 | K14: ='Monthly P&L'!C5 | L14: ='Monthly P&L'!D5 | M14: ='Monthly P&L'!E5 | N14: ='Monthly P&L'!F5 | O14: ='Monthly P&L'!G5
E15: Current (0-30 days) | G15: 168000
E16: 31-60 days | G16: 96000
E17: 61+ days | G17: 48000
E18: Accounts Payable | G18: 148000
E19: Days Sales Outstanding | G19: 48
E20: Current Ratio | G20: 1.8
B31: See the '13-Week Cash Flow' and 'Commentary' tabs for the full forward view.

Sheet Monthly P&L
A1: Summit Ridge Construction LLC — Monthly P&L (Actuals)
A2: All figures in USD. Blue cells are inputs (from bookkeeping export); black cells are formulas.
A4: P&L Line | B4: Feb-26 | C4: Mar-26 | D4: Apr-26 | E4: May-26 | F4: Jun-26 | G4: Jul-26
A5: Revenue | B5: 172000 | C5: 195000 | D5: 208000 | E5: 231000 | F5: 199000 | G5: 218400
A6: Cost of Goods Sold
A7: Materials | B7: 66000 | C7: 74000 | D7: 78000 | E7: 85000 | F7: 77000 | G7: 82000
A8: Subcontractors | B8: 39000 | C8: 43000 | D8: 46500 | E8: 52000 | F8: 44500 | G8: 49000
A9: Direct Labor | B9: 21400 | C9: 23800 | D9: 24900 | E9: 26800 | F9: 24000 | G9: 27300
A10: Total COGS | B10: =SUM(B7:B9) | C10: =SUM(C7:C9) | D10: =SUM(D7:D9) | E10: =SUM(E7:E9) | F10: =SUM(F7:F9) | G10: =SUM(G7:G9)
A11: Gross Profit | B11: =B5-B10 | C11: =C5-C10 | D11: =D5-D10 | E11: =E5-E10 | F11: =F5-F10 | G11: =G5-G10
A12: Gross Margin % | B12: =B11/B5 | C12: =C11/C5 | D12: =D11/D5 | E12: =E11/E5 | F12: =F11/F5 | G12: =G11/G5
A13: Operating Expenses
A14: Office Salaries | B14: 18000 | C14: 18000 | D14: 18000 | E14: 18000 | F14: 18000 | G14: 18000
A15: Rent & Utilities | B15: 4200 | C15: 4200 | D15: 4200 | E15: 4200 | F15: 4200 | G15: 4200
A16: Insurance | B16: 3100 | C16: 3100 | D16: 3100 | E16: 3100 | F16: 3100 | G16: 3100
A17: Vehicle & Equipment | B17: 3800 | C17: 3800 | D17: 3800 | E17: 3800 | F17: 3800 | G17: 3800
A18: Marketing | B18: 1500 | C18: 1500 | D18: 1500 | E18: 1500 | F18: 1500 | G18: 1500
A19: Admin & Other | B19: 3900 | C19: 3900 | D19: 3900 | E19: 3900 | F19: 3900 | G19: 3900
A20: Total OpEx | B20: =SUM(B14:B19) | C20: =SUM(C14:C19) | D20: =SUM(D14:D19) | E20: =SUM(E14:E19) | F20: =SUM(F14:F19) | G20: =SUM(G14:G19)
A21: Operating Income | B21: =B11-B20 | C21: =C11-C20 | D21: =D11-D20 | E21: =E11-E20 | F21: =F11-F20 | G21: =G11-G20
A22: Net Margin % | B22: =B21/B5 | C22: =C21/C5 | D22: =D21/D5 | E22: =E21/E5 | F22: =F21/F5 | G22: =G21/G5

Sheet 13-Week Cash Flow
A1: Summit Ridge Construction LLC — 13-Week Rolling Cash Flow Forecast
A2: Weeks beginning Monday. Blue = forecast inputs. Operating minimum cash target: $25,000 (amber if below, red if under $10k).
A4: Week beginning | B4: Aug 25 | C4: Sep 1 | D4: Sep 8 | E4: Sep 15 | F4: Sep 22 | G4: Sep 29 | H4: Oct 6 | I4: Oct 13 | J4: Oct 20 | K4: Oct 27 | L4: Nov 3 | M4: Nov 10 | N4: Nov 17
A5: Beginning Cash | B5: 142000 | C5: =B19 | D5: =C19 | E5: =D19 | F5: =E19 | G5: =F19 | H5: =G19 | I5: =H19 | J5: =I19 | ... N5: =M19
A6: Cash Inflows (collections)
A7: Customer Collections | B7: 52000 | C7: 24000 | D7: 18000 | E7: 28000 | F7: 31000 | G7: 46000 | H7: 38000 | I7: 118000 | J7: 34000 | K7: 41000 | L7: 37000 | M7: 44000 | N7: 39000
A8: Total Inflows | B8: =B7 | C8: =C7 | D8: =D7 | E8: =E7 | F8: =F7 | G8: =G7 | H8: =H7 | I8: =I7 | ... N8: =N7
A9: Cash Outflows
A10: Payroll | B10: 23000 | C10: 0 | D10: 23000 | E10: 0 | F10: 23000 | G10: 0 | H10: 23000 | I10: 0 | J10: 23000 | K10: 0 | L10: 23000 | M10: 0 | N10: 23000
A11: Materials / Suppliers | B11: 14000 | C11: 16000 | D11: 52000 | E11: 9000 | F11: 11000 | G11: 10000 | H11: 12000 | I11: 14000 | J11: 12000 | K11: 13000 | L11: 12000 | M11: 14000 | N11: 12000
A12: Subcontractors | B12: 9000 | C12: 11000 | D12: 8000 | E12: 12000 | F12: 9000 | G12: 8000 | H12: 9000 | I12: 11000 | J12: 9000 | K12: 10000 | L12: 9000 | M12: 11000 | N12: 10000
A13: Overhead (rent, ins, admin) | B13: 6500 | C13: 6500 | D13: 6500 | E13: 6500 | F13: 6500 | G13: 6500 | H13: 6500 | I13: 6500 | J13: 6500 | K13: 6500 | L13: 6500 | M13: 6500 | N13: 6500
A14: Loan / Equipment | B14: 4200 | C14: 0 | D14: 0 | E14: 0 | F14: 0 | G14: 4200 | H14: 0 | I14: 0 | J14: 0 | K14: 4200 | L14: 0 | M14: 0 | N14: 0
A15: Owner Draw | B15: 6000 | C15: 6000 | D15: 0 | E15: 6000 | F15: 0 | G15: 6000 | H15: 0 | I15: 6000 | J15: 0 | K15: 6000 | L15: 0 | M15: 6000 | N15: 0
A16: Estimated Taxes | B16: 0 | C16: 0 | D16: 0 | E16: 18000 | F16: 0 | G16: 0 | H16: 0 | I16: 0 | J16: 0 | K16: 0 | L16: 0 | M16: 0 | N16: 0
A17: Total Outflows | B17: =SUM(B10:B16) | C17: =SUM(C10:C16) | D17: =SUM(D10:D16) | E17: =SUM(E10:E16) | F17: =SUM(F10:F16) | G17: =SUM(G10:G16) | H17: =SUM(H10:H16) | I17: =SUM(I10:I16) | ... N17: =SUM(N10:N16)
A18: Net Cash Flow | B18: =B8-B17 | C18: =C8-C17 | D18: =D8-D17 | E18: =E8-E17 | F18: =F8-F17 | G18: =G8-G17 | H18: =H8-H17 | I18: =I8-I17 | ... N18: =N8-N17
A19: Ending Cash | B19: =B5+B18 | C19: =C5+C18 | D19: =D5+D18 | E19: =E5+E18 | F19: =F5+F18 | G19: =G5+G18 | H19: =H5+H18 | I19: =I5+I18 | ... N19: =N5+N18
A20: Below $25k minimum? | B20: =IF(B19<25000,"⚠ YES","OK") | C20: =IF(C19<25000,"⚠ YES","OK") | D20: =IF(D19<25000,"⚠ YES","OK") | E20: =IF(E19<25000,"⚠ YES","OK") | F20: =IF(F19<25000,"⚠ YES","OK") | G20: =IF(G19<25000,"⚠ YES","OK") | H20: =IF(H19<25000,"⚠ YES","OK") | I20: =IF(I19<25000,"⚠ YES","OK") | ... N20: =IF(N19<25000,"⚠ YES","OK")
A23: (chart data) | B23: Aug 25 | C23: Sep 1 | D23: Sep 8 | E23: Sep 15 | F23: Sep 22 | G23: Sep 29 | H23: Oct 6 | I23: Oct 13 | J23: Oct 20 | K23: Oct 27 | L23: Nov 3 | M23: Nov 10 | N23: Nov 17
A24: Ending Cash | B24: =B19 | C24: =C19 | D24: =D19 | E24: =E19 | F24: =F19 | G24: =G19 | H24: =H19 | I24: =I19 | ... N24: =N19
A25: Min Cash Target | B25: 25000 | C25: 25000 | D25: 25000 | E25: 25000 | F25: 25000 | G25: 25000 | H25: 25000 | I25: 25000 | J25: 25000 | K25: 25000 | L25: 25000 | M25: 25000 | N25: 25000

Sheet Commentary
A1: Summit Ridge Construction LLC — Monthly Commentary (July 2026)
B3: The headline
B4: You had another profitable month — $25,600 of net income on $218,400 of revenue (11.7% net margin), right in line with your six-month trend. Profit is not the problem. Timing is. Our 13-week forecast shows cash dropping to about $1,100 the week of October 6 — well below the $25,000 you want in the account to run comfortably. This is fixable, and you have roughly six weeks of runway to act.
B6: Why cash gets tight (even though you're profitable)
B7: Three things land close together: 1. The Hillcrest final draw ($96,000) slipped. It was expected the week of Sep 8 but is now tracking to Oct 13 — five weeks later. 2. Q3 estimated taxes ($18,000) are due Sep 15. 3. The Maple Grove material order ($52,000) hits Sep 8. Individually, none of these is a problem. Stacked in the same four weeks — while your big receivable is late — they drain the account faster than collections refill it. Cash stays under your $25k minimum from the week of Sep 15 through Oct 6.
B9: What we'd do about it — three options
B10: A. Pull Hillcrest forward. Offer the client a 1% early-payment discount ($960) to release the $96,000 draw in September instead of October. Even a partial payment resets the whole picture. This is the highest-leverage move. B. Push the big outflows past the tax date. Ask your Maple Grove supplier for net-45 terms on the $52,000 order, and pause owner draws for three weeks in September (frees ~$12,000). Together these keep the low point above $25k without touching the bank. C. Put a safety net in place now. Open a $50,000 line of credit while your numbers look strong — banks approve credit when you don't need it, not when you do. You may never draw on it, but it turns a scramble into a non-event.
B12: One thing to watch
B13: Days Sales Outstanding crept to 48 days, up from 41. Your final draws are being paid slowly — that's the same pattern that created this squeeze. Tightening billing the day a milestone completes (rather than at month-end) would pull cash in about a week sooner across every project and prevent the next crunch before it starts.
B15: Bottom line
B16: Strong operating month, one avoidable cash pinch on the horizon. Take option A plus a small piece of B and you sail through October above your minimum. Let's lock the plan on this month's strategy call — 45 minutes, and we'll pick the two moves that fit Hillcrest's client best.
B19: Prepared by Patino Davila Advisory · Questions before our call? patinodavilaadvisory@gmail.com / 973-856-0624
